LICENSE
README.txt
pyproject.toml
setup.py
hive.egg-info/PKG-INFO
hive.egg-info/SOURCES.txt
hive.egg-info/dependency_links.txt
hive.egg-info/requires.txt
hive.egg-info/top_level.txt
memhive/__init__.py
memhive/_version.py
memhive/asyncio.py
memhive/errors.py
memhive/memhive.py
memhive/core/errormech.c
memhive/core/map.c
memhive/core/memhive.c
memhive/core/module.c
memhive/core/queue.c
memhive/core/refqueue.c
memhive/core/sub.c
memhive/core/track.c
memhive/core/utils.c
tests/test_basics.py